{
    "name": "config",
    "profiles": [
        "default"
    ],
    "label": null,
    "version": "d79dfc4852baf3a85e1ea2ba4088692a4cf4ff9a",
    "state": null,
    "propertySources": [{
        "name": "https://github.com/tramanh9999/application-config-microservice-demo/application.yml (document #0)",
        "source": {
            "info.description": "Spring Cloud Samples",
            "info.url": "https://github.com/spring-cloud-samples",
            "eureka.client.serviceUrl.defaultZone": "http://localhost:8761/eureka/",
            "foo": "baz"
        }
    }]
}